triodos_fund_analyzer/.gitignore
triodos_fund_analyzer/CPI.py
triodos_fund_analyzer/__init__.py
triodos_fund_analyzer/app.py
triodos_fund_analyzer/funds.py
triodos_fund_analyzer-0.1.dev1.dist-info/entry_points.txt
triodos_fund_analyzer-0.1.dev1.dist-info/licenses/LICENSE
triodos_fund_analyzer-0.1.dev1.dist-info/WHEEL
triodos_fund_analyzer-0.1.dev1.dist-info/METADATA
triodos_fund_analyzer-0.1.dev1.dist-info/RECORD
