Metadata-Version: 2.4
Name: triodos_fund_analyzer
Version: 0.1.dev1
Summary: Tool to visualize Triodos fund histories
Author-email: Jan <152862650+j-haacker@users.noreply.github.com>
Requires-Python: >= 3.10
License-Expression: MIT
License-File: LICENSE
Requires-Dist: cbsodata
Requires-Dist: matplotlib
Requires-Dist: numpy
Requires-Dist: openpyxl
Requires-Dist: pandas
Requires-Dist: streamlit
Requires-Dist: flit ; extra == "dev"
Requires-Dist: ruff ; extra == "dev"
Requires-Dist: ipykernel ; extra == "notebooks"
Project-URL: Home, https://github.com/j-haacker/triodos-fund-analyzer
Provides-Extra: dev
Provides-Extra: notebooks
